{
  "DataSet": {
    "Title": "TestPoisonedBySpiderQuest03",
    "SauronDeckInfo": {
      "Id": null,
      "DeckList": []
    },
    "Stages": [
      {
        "Title": "Location301",
        "SoloGameSetup": [
          "FindThePath",
          "VeteranPatrol"
        ],
        "CoopGameSetup": [],
        "NextStages": [],
        "NextStageTitles": [
          ""
        ]
      }
    ],
    "Sequences": [],
    "Stories": []
  },
  "Version": "20171227104956566",
  "Key": "MainQuest",
  "SubKey": "TestPoisonedBySpiderQuest03",
  "RequiredClientVersion": "1.0",
  "InternalKey": "MainQuest_TestPoisonedBySpiderQuest03_20171227104956566"
}