{
  "DataSet": {
    "Title": "C001Q1",
    "SauronDeckInfo": {
      "Id": null,
      "DeckList": [
        {
          "Id": "HatchlingSpider",
          "Quantity": 3,
          "PlayOnce": false,
          "MinThreatLevel": 0,
          "MinDifficulty": 1,
          "MaxDifficulty": 4
        },
        {
          "Id": "WatchersInTheDark",
          "Quantity": 2,
          "PlayOnce": false,
          "MinThreatLevel": 0,
          "MinDifficulty": 1,
          "MaxDifficulty": 4
        },
        {
          "Id": "DarkSorcery",
          "Quantity": 2,
          "PlayOnce": false,
          "MinThreatLevel": 0,
          "MinDifficulty": 1,
          "MaxDifficulty": 4
        },
        {
          "Id": "Despair",
          "Quantity": 1,
          "PlayOnce": false,
          "MinThreatLevel": 0,
          "MinDifficulty": 1,
          "MaxDifficulty": 4
        },
        {
          "Id": "DrivenByShadow",
          "Quantity": 1,
          "PlayOnce": false,
          "MinThreatLevel": 0,
          "MinDifficulty": 1,
          "MaxDifficulty": 4
        },
        {
          "Id": "EyesOfTheForest",
          "Quantity": 1,
          "PlayOnce": false,
          "MinThreatLevel": 0,
          "MinDifficulty": 1,
          "MaxDifficulty": 4
        },
        {
          "Id": "ForestSpider",
          "Quantity": 2,
          "PlayOnce": false,
          "MinThreatLevel": 0,
          "MinDifficulty": 1,
          "MaxDifficulty": 4
        },
        {
          "Id": "GatheringGloom",
          "Quantity": 1,
          "PlayOnce": false,
          "MinThreatLevel": 0,
          "MinDifficulty": 1,
          "MaxDifficulty": 4
        },
        {
          "Id": "MirkwoodFlock",
          "Quantity": 1,
          "PlayOnce": false,
          "MinThreatLevel": 0,
          "MinDifficulty": 1,
          "MaxDifficulty": 4
        },
        {
          "Id": "PursuedByShadow",
          "Quantity": 1,
          "PlayOnce": false,
          "MinThreatLevel": 0,
          "MinDifficulty": 1,
          "MaxDifficulty": 4
        },
        {
          "Id": "SpiesofShadow",
          "Quantity": 2,
          "PlayOnce": false,
          "MinThreatLevel": 0,
          "MinDifficulty": 1,
          "MaxDifficulty": 4
        },
        {
          "Id": "TreacherousFog",
          "Quantity": 1,
          "PlayOnce": false,
          "MinThreatLevel": 0,
          "MinDifficulty": 1,
          "MaxDifficulty": 4
        },
        {
          "Id": "UnderTheShadow",
          "Quantity": 1,
          "PlayOnce": false,
          "MinThreatLevel": 0,
          "MinDifficulty": 1,
          "MaxDifficulty": 4
        },
        {
          "Id": "Unwavering",
          "Quantity": 1,
          "PlayOnce": false,
          "MinThreatLevel": 0,
          "MinDifficulty": 1,
          "MaxDifficulty": 4
        },
        {
          "Id": "Veteran",
          "Quantity": 1,
          "PlayOnce": false,
          "MinThreatLevel": 0,
          "MinDifficulty": 1,
          "MaxDifficulty": 4
        },
        {
          "Id": "Enfeebled",
          "Quantity": 1,
          "PlayOnce": false,
          "MinThreatLevel": 0,
          "MinDifficulty": 1,
          "MaxDifficulty": 4
        },
        {
          "Id": "EvilStorm",
          "Quantity": 1,
          "PlayOnce": false,
          "MinThreatLevel": 0,
          "MinDifficulty": 1,
          "MaxDifficulty": 4
        },
        {
          "Id": "GreedyFingers",
          "Quantity": 1,
          "PlayOnce": false,
          "MinThreatLevel": 0,
          "MinDifficulty": 1,
          "MaxDifficulty": 4
        },
        {
          "Id": "LowOnSupplies",
          "Quantity": 1,
          "PlayOnce": false,
          "MinThreatLevel": 0,
          "MinDifficulty": 1,
          "MaxDifficulty": 4
        },
        {
          "Id": "PoisonedBySpiders",
          "Quantity": 1,
          "PlayOnce": false,
          "MinThreatLevel": 0,
          "MinDifficulty": 1,
          "MaxDifficulty": 4
        },
        {
          "Id": "SpiderGuard",
          "Quantity": 2,
          "PlayOnce": false,
          "MinThreatLevel": 0,
          "MinDifficulty": 1,
          "MaxDifficulty": 4
        },
        {
          "Id": "ThickWebs",
          "Quantity": 1,
          "PlayOnce": false,
          "MinThreatLevel": 0,
          "MinDifficulty": 1,
          "MaxDifficulty": 4
        },
        {
          "Id": "UnderTheWatchfulEye",
          "Quantity": 1,
          "PlayOnce": false,
          "MinThreatLevel": 0,
          "MinDifficulty": 1,
          "MaxDifficulty": 4
        },
        {
          "Id": "WatchfulEyes",
          "Quantity": 2,
          "PlayOnce": false,
          "MinThreatLevel": 0,
          "MinDifficulty": 1,
          "MaxDifficulty": 4
        },
        {
          "Id": "GiantSpider",
          "Quantity": 1,
          "PlayOnce": false,
          "MinThreatLevel": 0,
          "MinDifficulty": 1,
          "MaxDifficulty": 4
        },
        {
          "Id": "HiveGuardian",
          "Quantity": 2,
          "PlayOnce": false,
          "MinThreatLevel": 0,
          "MinDifficulty": 1,
          "MaxDifficulty": 4
        },
        {
          "Id": "KingSpider",
          "Quantity": 1,
          "PlayOnce": false,
          "MinThreatLevel": 0,
          "MinDifficulty": 1,
          "MaxDifficulty": 4
        },
        {
          "Id": "MirkwoodBroodmother",
          "Quantity": 1,
          "PlayOnce": false,
          "MinThreatLevel": 0,
          "MinDifficulty": 1,
          "MaxDifficulty": 4
        },
        {
          "Id": "SpidersOfMirkwood",
          "Quantity": 1,
          "PlayOnce": false,
          "MinThreatLevel": 0,
          "MinDifficulty": 1,
          "MaxDifficulty": 4
        },
        {
          "Id": "TheNecromancersReach",
          "Quantity": 1,
          "PlayOnce": false,
          "MinThreatLevel": 0,
          "MinDifficulty": 1,
          "MaxDifficulty": 4
        },
        {
          "Id": "TurnedAround",
          "Quantity": 1,
          "PlayOnce": false,
          "MinThreatLevel": 0,
          "MinDifficulty": 1,
          "MaxDifficulty": 4
        }
      ]
    },
    "Stages": [
      {
        "Title": "C001Q1L1",
        "SoloGameSetup": [
          "InvestigateTheGlade",
          "HiveGuardian",
          "ForestSpider",
          "ForestSpider",
          "GiantSpider"
        ],
        "CoopGameSetup": [],
        "NextStages": [],
        "NextStageTitles": [
          "C001Q1L2"
        ],
        "FateCardList": [
          {
            "Id": "BilbosPack",
            "Threshold": 2
          },
          {
            "Id": "AddercopAddercop",
            "Threshold": 4
          }
        ],
        "ThreatCardList": [],
        "NarrativeCount": 2,
        "NarrativeTextList": [
          "Q_STAGE_C001Q1L1_TEXT_0",
          "Q_STAGE_C001Q1L1_TEXT_1"
        ]
      },
      {
        "Title": "C001Q1L2",
        "SoloGameSetup": [
          "FindAWayAcross",
          "WildBear",
          "RockAdder",
          "BlackForestBats",
          ""
        ],
        "CoopGameSetup": [],
        "NextStages": [],
        "NextStageTitles": [
          "C001Q1L3"
        ],
        "FateCardList": [
          {
            "Id": "UlahidMushrooms",
            "Threshold": 2
          },
          {
            "Id": "CordialOfSleep",
            "Threshold": 4
          }
        ],
        "ThreatCardList": [
          {
            "Id": "UnsteadyFooting",
            "Threshold": 3
          }
        ],
        "NarrativeCount": 3,
        "NarrativeTextList": [
          "Q_STAGE_C001Q1L2_TEXT_0",
          "Q_STAGE_C001Q1L2_TEXT_1",
          "Q_STAGE_C001Q1L2_TEXT_2"
        ]
      },
      {
        "Title": "C001Q1L3",
        "SoloGameSetup": [
          "GreatBear"
        ],
        "CoopGameSetup": [],
        "NextStages": [],
        "NextStageTitles": [
          "C001Q1L4"
        ],
        "FateCardList": [
          {
            "Id": "WildHoney",
            "Threshold": 6
          },
          {
            "Id": "GrimbeornFate",
            "Threshold": 8
          }
        ],
        "ThreatCardList": [
          {
            "Id": "MoreToBear",
            "Threshold": 2
          }
        ],
        "NarrativeCount": 1,
        "NarrativeTextList": [
          "Q_STAGE_C001Q1L3_TEXT_0"
        ]
      },
      {
        "Title": "C001Q1L4",
        "SoloGameSetup": [
          "ThrashingCocoon",
          "ForestSpider",
          "GiantSpider",
          "SpidersOfMirkwood",
          "SpiderGuard"
        ],
        "CoopGameSetup": [],
        "NextStages": [],
        "NextStageTitles": [
          ""
        ],
        "FateCardList": [],
        "ThreatCardList": [],
        "NarrativeCount": 1,
        "NarrativeTextList": [
          "Q_STAGE_C001Q1L4_TEXT_0"
        ]
      }
    ],
    "Sequences": [],
    "Stories": [],
    "VictoryCount": 2,
    "VictoryTextList": [
      "Q_QUEST_C001Q1_TEXT_0",
      "Q_QUEST_C001Q1_TEXT_1"
    ],
    "VictoryVoiceList": [
      "C001Q1_VictoryVoice_1",
      "C001Q1_VictoryVoice_2"
    ],
    "FateCardList": [
      {
        "Id": "TheGuiltOfDwarves",
        "Threshold": 7
      }
    ],
    "ThreatCardList": [
      {
        "Id": "SpidersDescend",
        "Threshold": 1
      },
      {
        "Id": "WaveOfFear",
        "Threshold": 2
      },
      {
        "Id": "WebsEverywhere",
        "Threshold": 3
      }
    ],
    "AIBehavior": "PassiveAI"
  },
  "Version": "20180826203641080",
  "Key": "MainQuest",
  "SubKey": "C001Q1",
  "RequiredClientVersion": "1.0",
  "InternalKey": "MainQuest_C001Q1_20180826203641080"
}