{
  "DataSet": [
    "ConflictAtTheCarrock",
    "DelCampTestQuest01",
    "DelCampTestQuest02",
    "DelCampTestQuest03",
    "DelCampTestQuest04",
    "DelCampTestQuest05",
    "FliesAndSpiders",
    "JourneyDownTheAnduin",
    "LostInMirkwood",
    "NSKTESTQuest01",
    "NSKTESTQuest02",
    "NSKTESTQuest03",
    "NSKTESTQuest04",
    "NSKTESTQuest05",
    "PassageThroughMirkwood",
    "Test0208Quest01",
    "Test0208Quest02",
    "Test0208Quest03",
    "Test0208Quest04",
    "Test0208Quest05",
    "TestPoisonedBySpiderQuest01",
    "TestPoisonedBySpiderQuest02",
    "TestPoisonedBySpiderQuest03",
    "TestPoisonedBySpiderQuest04",
    "TestPoisonedBySpiderQuest05",
    "TestSauronAI1225Quest01",
    "TestSauronAI1225Quest02",
    "TestSauronAI1225Quest03",
    "TestSauronAI1225Quest04",
    "TestSauronAI1225Quest05"
  ],
  "Version": "20180208223629865",
  "Key": "QuestTitles",
  "SubKey": null,
  "RequiredClientVersion": "1.0",
  "InternalKey": "QuestTitles20180208223629865"
}