{
  "CardData": {
    "Id": "Aragorn",
    "Owner": "Player",
    "CardType": 5,
    "ShopType": "Starter",
    "Cost": 11,
    "QuestPoints": 0,
    "Attack": 2,
    "Willpower": 2,
    "Health": 11,
    "Trait": "Dúnedan ",
    "Rarity": 3,
    "Sphere": 0,
    "SphereLevel": 0,
    "Revision": "test",
    "PlayVFX": "Effect_HeroCardLight 1",
    "PlaySFX": "ally_ent_both01_e",
    "AttackVFX": "",
    "AttackSFX": "event_attack_sword_e",
    "DeathVFX": "Effect_Death3",
    "DeathSFX": "die_both_e",
    "FlavorText": "",
    "ArtistName": "",
    "Status": "Ready"
  },
  "Localization": {
    "Title": "‰Aragorn  ",
    "Text": "Power: Ready Aragorn (cost 1)"
  }
}