{
  "CardData": {
    "Id": "ATest181120",
    "Owner": "Player",
    "CardType": 5,
    "ShopType": "Starter",
    "Cost": 27,
    "QuestPoints": 0,
    "Attack": 9,
    "Willpower": 9,
    "Health": 9,
    "Trait": "Noldor",
    "Rarity": 4,
    "Sphere": 0,
    "SphereLevel": 0,
    "Revision": "test",
    "PlayVFX": "",
    "PlaySFX": "",
    "AttackVFX": "",
    "AttackSFX": "",
    "DeathVFX": "",
    "DeathSFX": "",
    "FlavorText": "[do not translate]tester\ntest",
    "ArtistName": "shisonghua",
    "Status": "WIP"
  },
  "Localization": {
    "Title": "testing card",
    "Text": "[do not translate]a playground for card script testing,"
  }
}