{
  "CardData": {
    "Id": "ATest18040401",
    "Owner": "Player",
    "CardType": 4,
    "ShopType": "",
    "Cost": 0,
    "QuestPoints": 0,
    "Attack": 0,
    "Willpower": 1,
    "Health": 0,
    "Trait": "",
    "Rarity": 0,
    "Sphere": 2,
    "SphereLevel": 0,
    "Revision": "test",
    "PlayVFX": "",
    "PlaySFX": "",
    "AttackVFX": "",
    "AttackSFX": "",
    "DeathVFX": "",
    "DeathSFX": "",
    "FlavorText": "C_ATEST18040401_FLAVOR",
    "ArtistName": "",
    "Status": "WIP",
    "ArtworkMD5": null,
    "BannerMD5": null,
    "IconMD5": null
  },
  "Localization": null
}