{
  "CardData": {
    "Id": "BorneAloft",
    "Owner": "Player",
    "CardType": 4,
    "ShopType": "Valor",
    "Cost": 1,
    "QuestPoints": 0,
    "Attack": 0,
    "Willpower": 0,
    "Health": 0,
    "Trait": "Preparation",
    "Rarity": 0,
    "Sphere": 3,
    "SphereLevel": 1,
    "Revision": "test",
    "PlayVFX": "",
    "PlaySFX": "",
    "AttackVFX": "",
    "AttackSFX": "",
    "DeathVFX": "",
    "DeathSFX": "",
    "FlavorText": "\"Very well,\" said Gandalf. \"Take us where and as far as you will!\" \n<i>–The Hobbit</i>",
    "ArtistName": "Salvador Trakal",
    "Status": "Ready",
    "ArtworkMD5": "160330f715d9bef4f34070d92d431362",
    "BannerMD5": null,
    "IconMD5": null
  },
  "Localization": {
    "Title": "Borne Aloft",
    "Text": "Your next defeated Ally returns to your hand"
  }
}