{
  "CardData": {
    "Id": "DunedainQuest",
    "Owner": "Player",
    "CardType": 1,
    "ShopType": "Starter",
    "Cost": 3,
    "QuestPoints": 0,
    "Attack": 0,
    "Willpower": 0,
    "Health": 0,
    "Trait": "Special",
    "Rarity": 3,
    "Sphere": 0,
    "SphereLevel": 1,
    "Revision": "test",
    "PlayVFX": "",
    "PlaySFX": "",
    "AttackVFX": "",
    "AttackSFX": "",
    "DeathVFX": "",
    "DeathSFX": "",
    "FlavorText": "C_DUNEDAINQUEST_FLAVOR",
    "ArtistName": "",
    "Status": "None",
    "ArtworkMD5": "8306218aea8165e27525611e5912faf4",
    "BannerMD5": "03c8f53c671a67d3f8e0ceaddfa8c353",
    "IconMD5": "af8783c9a91b07f8fa96628ef929fa3d"
  },
  "Localization": {
    "Title": "Dunedain Quest",
    "Text": "C_DUNEDAINQUEST_TEXT"
  }
}