{
  "CardData": {
    "Id": "HalflingDetermination",
    "Owner": "Player",
    "CardType": 4,
    "ShopType": "Pack_01",
    "Cost": 2,
    "QuestPoints": 0,
    "Attack": 0,
    "Willpower": 0,
    "Health": 0,
    "Trait": "",
    "Rarity": 0,
    "Sphere": 1,
    "SphereLevel": 1,
    "Revision": "test",
    "PlayVFX": "",
    "PlaySFX": "",
    "AttackVFX": "",
    "AttackSFX": "",
    "DeathVFX": "",
    "DeathSFX": "",
    "FlavorText": "",
    "ArtistName": "",
    "Status": "Ready"
  },
  "Localization": {
    "Title": "Halfling Determination",
    "Text": "Restore 4 Health to each Hobbit"
  }
}