{
  "CardData": {
    "Id": "Sting",
    "Owner": "Player",
    "CardType": 1,
    "ShopType": "HeroPack_TheRetiredBurglar",
    "Cost": 3,
    "QuestPoints": 0,
    "Attack": 0,
    "Willpower": 0,
    "Health": 0,
    "Trait": "Weapon",
    "Rarity": 4,
    "Sphere": 3,
    "SphereLevel": 2,
    "Revision": null,
    "PlayVFX": "",
    "PlaySFX": "",
    "AttackVFX": "",
    "AttackSFX": "",
    "DeathVFX": "",
    "DeathSFX": "",
    "FlavorText": "",
    "ArtistName": "",
    "Status": "WIP",
    "CardOffsetX": 1.0,
    "CardOffsetY": 1.0,
    "CardScale": 1.0,
    "CameoOffsetX": 1.0,
    "CameoOffsetY": 1.0,
    "CameoScale": 1.0,
    "CombatValue": 0,
    "ResolutionValue": 0,
    "ComboList": [],
    "ArtworkMD5": "611d36023456dcf54cfbbd5936ec2b2c",
    "BannerMD5": "bbb01fb4d45aedf2fa33cf4aec3ea032",
    "IconMD5": "d28750b4ad9781944a00f9b37d889c96"
  },
  "Localization": {
    "Title": "Sting",
    "Text": "Gain +1 <size=120%><sprite=0></size>. \nGain an extra <size=120%><sprite=0></size> when attacking <b><i>Orc</i></b> or <b><i>Spider</i></b> enemies"
  }
}