{
  "CardData": {
    "Id": "BlackBlood",
    "Owner": "Sauron",
    "CardType": 9,
    "ShopType": "Starter",
    "Cost": 1,
    "QuestPoints": 0,
    "Attack": 0,
    "Willpower": 0,
    "Health": 0,
    "Trait": "",
    "Rarity": 0,
    "Sphere": 2,
    "SphereLevel": 0,
    "Revision": "test",
    "PlayVFX": "",
    "PlaySFX": "",
    "AttackVFX": "",
    "AttackSFX": "",
    "DeathVFX": "",
    "DeathSFX": "",
    "FlavorText": "Then Pippin stabbed upwards, and the written blade of Westernesse pierced through the hide and went deep into the vitals of the troll, and his black blood came gushing out. \n—<i>The Return of the King</i>",
    "ArtistName": "Magali Villeneuve",
    "Status": "Ready",
    "ArtworkMD5": "20e33e8cb54b4a44dc7eb1d06a0d9228",
    "BannerMD5": null,
    "IconMD5": "858ed83a94277742d7ee74e079fd848b"
  },
  "Localization": {
    "Title": "Black Blood",
    "Text": "Restore 2 Health to each Troll"
  }
}