{
  "CardData": {
    "Id": "GreatBear",
    "Owner": "Sauron",
    "CardType": 2,
    "ShopType": "",
    "Cost": 0,
    "QuestPoints": 0,
    "Attack": 4,
    "Willpower": 0,
    "Health": 9,
    "Trait": "Creature",
    "Rarity": 0,
    "Sphere": 2,
    "SphereLevel": 0,
    "Revision": null,
    "PlayVFX": "",
    "PlaySFX": "",
    "AttackVFX": "",
    "AttackSFX": "",
    "DeathVFX": "",
    "DeathSFX": "",
    "FlavorText": "",
    "CannotTriggerReason": "",
    "ArtistName": "",
    "Status": "WIP",
    "CardOffsetX": 1.06,
    "CardOffsetY": 0.83,
    "CardScale": 0.8,
    "CameoOffsetX": 1.05,
    "CameoOffsetY": 0.83,
    "CameoScale": 0.8,
    "CombatValue": 0,
    "ResolutionValue": 0,
    "CanBePlayedDuringTravel": true,
    "ComboList": [],
    "ArtworkMD5": "a16afa40a6f5347dd9674a58d0a3ebf7",
    "BannerMD5": "718566a0c9430940c52bc9c17230e584",
    "IconMD5": "90b22c1773c0bbe36bed77f8985369ff"
  },
  "Localization": {
    "Title": "Kirous",
    "Text": "Exhaust any Character that is damaged by this card"
  }
}