{
  "CardData": {
    "Id": "SwirlingEddy",
    "Owner": "Sauron",
    "CardType": 6,
    "ShopType": "",
    "Cost": 0,
    "QuestPoints": 4,
    "Attack": 0,
    "Willpower": 0,
    "Health": 0,
    "Trait": "",
    "Rarity": 0,
    "Sphere": 2,
    "SphereLevel": 0,
    "Revision": "test",
    "PlayVFX": "",
    "PlaySFX": "",
    "AttackVFX": "",
    "AttackSFX": "",
    "DeathVFX": "",
    "DeathSFX": "",
    "FlavorText": "C_SWIRLINGEDDY_FLAVOR",
    "ArtistName": "",
    "Status": "None",
    "ArtworkMD5": null,
    "BannerMD5": null,
    "IconMD5": null
  },
  "Localization": {
    "Title": "Swirling Eddy",
    "Text": "At end of round: Discard a random card from your deck"
  }
}